reinforcement_terminals/__init__.py
reinforcement_terminals/detect_age_gender/__init__.py
reinforcement_terminals/detect_age_gender/inference.py
reinforcement_terminals/detect_age_gender/model/__init__.py
reinforcement_terminals/detect_age_gender/model/config_eag.py
reinforcement_terminals-0.0.129.dist-info/LICENSE
reinforcement_terminals-0.0.129.dist-info/METADATA
reinforcement_terminals-0.0.129.dist-info/WHEEL
reinforcement_terminals-0.0.129.dist-info/top_level.txt
reinforcement_terminals-0.0.129.dist-info/RECORD
