Metadata-Version: 2.1
Name: reinforcement-terminals
Version: 0.0.129
Summary: Age and Gender Detection added to module
Home-page: https://github.com/SamipThulung/reinforcement_terminals
Author: Samip Rai
Author-email: samipthulung3@gmail.com
License: UNKNOWN
Platform: UNKNOWN
Classifier: Programming Language :: Python :: 3
Classifier: License :: OSI Approved :: MIT License
Classifier: Operating System :: OS Independent
Requires-Python: >=3.6
Requires-Dist: numpy
Requires-Dist: Keras (==2.2.4)
